<?xml version='1.0' encoding='utf-8'?>
<ComicInfo xmlns:xsi="http://www.w3.org/2001/XMLSchema-instance" xsi:schemaLocation="https://anansi-project.github.io/docs/comicinfo/schemas/v2.1">
  <Characters>Vampirella,Jack Halloran</Characters>
  <Colorist>Adriano Lucas,Vinicius Andrade,Adriano Lucas,Vinicius Andrade</Colorist>
  <GTIN>urn:comicvine:4000-329514</GTIN>
  <Inker>Ivan Rodriguez,Ivan Rodriguez</Inker>
  <Letterer>Marshall Dillon,Marshall Dillon</Letterer>
  <Month>4</Month>
  <Notes>Tagged with comicbox 1.1.1 on 2024-03-13T20:37:13 [Issue ID 4000-329514] urn:comicvine:4000-329514
Tagged with ComicTagger 1.6.0a13.dev122 using info from Grand Comics Database on 2024-06-16 19:17:27. [Issue ID 936478]</Notes>
  <Number>3</Number>
  <PageCount>24</PageCount>
  <Pages>
    <Page Image="0" ImageSize="965751" Type="FrontCover" />
    <Page Image="1" ImageSize="921330" />
    <Page Image="2" ImageSize="1291405" />
    <Page Image="3" ImageSize="1413220" />
    <Page Image="4" ImageSize="1227125" />
    <Page Image="5" ImageSize="1225559" />
    <Page Image="6" ImageSize="1201114" />
    <Page Image="7" ImageSize="1928809" />
    <Page Image="8" ImageSize="1559052" />
    <Page Image="9" ImageSize="1261708" />
    <Page Image="10" ImageSize="1260931" />
    <Page Image="11" ImageSize="1287317" />
    <Page Image="12" ImageSize="1109979" />
    <Page Image="13" ImageSize="1275372" />
    <Page Image="14" ImageSize="1413151" />
    <Page Image="15" ImageSize="1255629" />
    <Page Image="16" ImageSize="1451275" />
    <Page Image="17" ImageSize="1484371" />
    <Page Image="18" ImageSize="1300171" />
    <Page Image="19" ImageSize="1512818" />
    <Page Image="20" ImageSize="1520959" />
    <Page Image="21" ImageSize="1531560" />
    <Page Image="22" ImageSize="997777" />
    <Page Image="23" ImageSize="991563" />
  </Pages>
  <Penciller>Ivan Rodriguez,Ivan Rodriguez</Penciller>
  <Publisher>Dynamite Entertainment</Publisher>
  <ScanInformation>.  (Digital-Empire)</ScanInformation>
  <Series>Vampirella vs. Dracula</Series>
  <Summary>With Vampirella trapped in Dracula's shifting past, Jack Halloran, is left to deal with the machinations of his modern-day incarnation, the mysterious and deadly Dragunsun. But when changes to the eternal narrative first chronicled by Bram Stoker ripple through the present, each of the characters affected, in all the timelines they cross, must adjust, adapt and reorient themselves if they wish to see the story through until the end, much less survive the effects. And when the strange and mystical "Order of the Dragon" make their presence known, everyone learns this is all neither an accident, nor a game.

https://comicvine.gamespot.com/vampirella-vs-dracula-3/4000-329514/</Summary>
  <Title>Dracula</Title>
  <Volume>2012</Volume>
  <Web>https://comicvine.gamespot.com/vampirella-vs-dracula-3/4000-329514/</Web>
  <Writer>Joe Harris,Joe Harris</Writer>
  <Year>2012</Year>
  <Count>6</Count>
  <Genre>Horror-suspense</Genre>
  <LanguageISO>en</LanguageISO>
  <Format>Limited Series</Format>
  <Editor>Joseph Rybandt</Editor>
</ComicInfo>