<?xml version='1.0' encoding='utf-8'?>
<ComicInfo xmlns:xsi="http://www.w3.org/2001/XMLSchema-instance" xsi:schemaLocation="https://anansi-project.github.io/docs/comicinfo/schemas/v2.1">
  <Day>22</Day>
  <GTIN>urn:comicvine:4000-468501</GTIN>
  <Inker>John Christmas</Inker>
  <Month>10</Month>
  <Notes>Tagged with comicbox 1.1.1 on 2024-03-13T19:24:15 [Issue ID 4000-468501] urn:comicvine:4000-468501
Tagged with ComicTagger 1.6.0a13.dev122 using info from Grand Comics Database on 2024-06-17 23:47:52. [Issue ID 1265520]</Notes>
  <Number>12</Number>
  <PageCount>33</PageCount>
  <Pages>
    <Page Image="0" ImageSize="2145709" Type="FrontCover" />
    <Page Image="1" ImageSize="1331659" />
    <Page Image="2" ImageSize="1555483" />
    <Page Image="3" ImageSize="1333244" />
    <Page Image="4" ImageSize="1301996" />
    <Page Image="5" ImageSize="1684704" />
    <Page Image="6" ImageSize="1345309" />
    <Page Image="7" ImageSize="1394547" />
    <Page Image="8" ImageSize="1421843" />
    <Page Image="9" ImageSize="1395639" />
    <Page Image="10" ImageSize="1177141" />
    <Page Image="11" ImageSize="1381048" />
    <Page Image="12" ImageSize="1368633" />
    <Page Image="13" ImageSize="1591163" />
    <Page Image="14" ImageSize="1443828" />
    <Page Image="15" ImageSize="1480863" />
    <Page Image="16" ImageSize="1599048" />
    <Page Image="17" ImageSize="1214392" />
    <Page Image="18" ImageSize="1121668" />
    <Page Image="19" ImageSize="1373304" />
    <Page Image="20" ImageSize="1507785" />
    <Page Image="21" ImageSize="1524223" />
    <Page Image="22" ImageSize="1248636" />
    <Page Image="23" ImageSize="1253342" />
    <Page Image="24" ImageSize="1676886" />
    <Page Image="25" ImageSize="1787108" />
    <Page Image="26" ImageSize="1574996" />
    <Page Image="27" ImageSize="1877882" />
    <Page Image="28" ImageSize="1325233" />
    <Page Image="29" ImageSize="1885640" />
    <Page Image="30" ImageSize="1545674" />
    <Page Image="31" ImageSize="2311040" />
    <Page Image="32" ImageSize="173768" />
  </Pages>
  <Penciller>John Christmas</Penciller>
  <Publisher>Image</Publisher>
  <Series>Sheltered</Series>
  <Summary>THE COUNTDOWN TO THE END CONTINUES. The outside world is closing in and the two factions fighting within the gates of Safe Haven have turned their sanctuary into a war zone. The end of the world is now the LEAST of their concerns.

Tagged with the ninjas.walk.alone fork of ComicTagger 1.3.5 using info from Comic Vine on 2024-02-04 20:10:59.  [Issue ID 468501]

https://comicvine.gamespot.com/sheltered-12/4000-468501/</Summary>
  <Volume>2013</Volume>
  <Web>https://comicvine.gamespot.com/sheltered-12/4000-468501/</Web>
  <Writer>Ed Brisson</Writer>
  <Year>2014</Year>
  <Count>15</Count>
  <LanguageISO>en</LanguageISO>
</ComicInfo>