<ComicInfo xmlns:xsi="http://www.w3.org/2001/XMLSchema-instance" xsi:schemaLocation="https://anansi-project.github.io/docs/comicinfo/schemas/v2.1">
  <Colorist>Angus McKie</Colorist>
  <Editor>Nicole Wiley Boose</Editor>
  <GTIN>urn:comicvine:4000-336111</GTIN>
  <Inker>Andy Lanning,Dave Gibbons</Inker>
  <Locations>Beijing,Hawaii,London,England,China</Locations>
  <Month>7</Month>
  <Notes>Tagged with comicbox 1.1.1 on 2024-03-13T14:31:23 [Issue ID 4000-336111] urn:comicvine:4000-336111
Tagged with ComicTagger 1.6.0a13.dev122 using info from Grand Comics Database on 2024-06-15 15:06:41. [Issue ID 944845]</Notes>
  <Number>2</Number>
  <PageCount>29</PageCount>
  <Pages>
    <Page Image="0" ImageSize="1853967" Type="FrontCover" />
    <Page Image="1" ImageSize="1851114" />
    <Page Image="2" ImageSize="914319" />
    <Page Image="3" ImageSize="1653219" />
    <Page Image="4" ImageSize="1882457" />
    <Page Image="5" ImageSize="1864705" />
    <Page Image="6" ImageSize="1616004" />
    <Page Image="7" ImageSize="1819806" />
    <Page Image="8" ImageSize="1535265" />
    <Page Image="9" ImageSize="1689544" />
    <Page Image="10" ImageSize="1695250" />
    <Page Image="11" ImageSize="1436527" />
    <Page Image="12" ImageSize="1782664" />
    <Page Image="13" ImageSize="1656615" />
    <Page Image="14" ImageSize="1912559" />
    <Page Image="15" ImageSize="1641256" />
    <Page Image="16" ImageSize="1811559" />
    <Page Image="17" ImageSize="1350456" />
    <Page Image="18" ImageSize="1883828" />
    <Page Image="19" ImageSize="1720853" />
    <Page Image="20" ImageSize="1828856" />
    <Page Image="21" ImageSize="1570634" />
    <Page Image="22" ImageSize="1792259" />
    <Page Image="23" ImageSize="1248879" />
    <Page Image="24" ImageSize="1461558" />
    <Page Image="25" ImageSize="1393158" />
    <Page Image="26" ImageSize="654166" />
    <Page Image="27" ImageSize="1166076" />
    <Page Image="28" ImageSize="1230339" />
  </Pages>
  <Penciller>Dave Gibbons</Penciller>
  <Publisher>Marvel</Publisher>
  <Series>The Secret Service</Series>
  <Summary>The world's greatest secret agent is on the most exciting case of his  career. But will the end of the world as we know it take a back seat to  training his street-punk nephew to be the next James Bond? The young  man's preparation now begins in earnest, saving him from a life of  desperation. Meanwhile, what's the secret link between a series of  kidnapped science fiction stars and the murder of an entire town in  Middle America?</Summary>
  <Tags>Beijing,Hawaii,People's Republic of China,London,England</Tags>
  <Volume>2012</Volume>
  <Web>https://comicvine.gamespot.com/the-secret-service-2/4000-336111/</Web>
  <Writer>Mark Millar,Matthew Vaughn</Writer>
  <Year>2012</Year>
  <Count>6</Count>
  <CoverArtist>Dave Gibbons</CoverArtist>
  <Genre>Spy</Genre>
  <LanguageISO>en</LanguageISO>
  <Format>Limited Series</Format>
</ComicInfo>