<?xml version='1.0' encoding='utf-8'?>
<ComicInfo xmlns:xsi="http://www.w3.org/2001/XMLSchema-instance" xsi:schemaLocation="https://anansi-project.github.io/docs/comicinfo/schemas/v2.1">
  <AgeRating>Mature 17+</AgeRating>
  <Colorist>Gaston Zubeklia</Colorist>
  <Count>6</Count>
  <Format>Limited Series</Format>
  <Inker>Emiliano Urdinoloa</Inker>
  <Letterer>Joel Rodriguez</Letterer>
  <Notes>Tagged with comicbox 1.2.0 on 2024-10-07T19:51:50</Notes>
  <Number>5</Number>
  <PageCount>27</PageCount>
  <Pages>
    <Page DoublePage="False" Image="0" ImageHeight="3886" ImageSize="1908492" ImageWidth="2560" Type="FrontCover" />
    <Page DoublePage="False" Image="1" ImageHeight="3886" ImageSize="1955444" ImageWidth="2560" />
    <Page DoublePage="False" Image="2" ImageHeight="3886" ImageSize="2436338" ImageWidth="2560" />
    <Page DoublePage="False" Image="3" ImageHeight="3886" ImageSize="1970646" ImageWidth="2560" />
    <Page DoublePage="False" Image="4" ImageHeight="3886" ImageSize="2302522" ImageWidth="2560" />
    <Page DoublePage="False" Image="5" ImageHeight="3886" ImageSize="2479746" ImageWidth="2560" />
    <Page DoublePage="False" Image="6" ImageHeight="3886" ImageSize="2034889" ImageWidth="2560" />
    <Page DoublePage="False" Image="7" ImageHeight="3886" ImageSize="2317721" ImageWidth="2560" />
    <Page DoublePage="False" Image="8" ImageHeight="3886" ImageSize="2182304" ImageWidth="2560" />
    <Page DoublePage="True" Image="9" ImageHeight="3886" ImageSize="5124487" ImageWidth="5027" />
    <Page DoublePage="False" Image="10" ImageHeight="3886" ImageSize="2299281" ImageWidth="2560" />
    <Page DoublePage="False" Image="11" ImageHeight="3886" ImageSize="2386881" ImageWidth="2560" />
    <Page DoublePage="False" Image="12" ImageHeight="3886" ImageSize="2033761" ImageWidth="2560" />
    <Page DoublePage="False" Image="13" ImageHeight="3886" ImageSize="2275616" ImageWidth="2560" />
    <Page DoublePage="False" Image="14" ImageHeight="3886" ImageSize="1852062" ImageWidth="2560" />
    <Page DoublePage="False" Image="15" ImageHeight="3886" ImageSize="2494081" ImageWidth="2560" />
    <Page DoublePage="False" Image="16" ImageHeight="3886" ImageSize="2035206" ImageWidth="2560" />
    <Page DoublePage="False" Image="17" ImageHeight="3886" ImageSize="2572330" ImageWidth="2560" />
    <Page DoublePage="False" Image="18" ImageHeight="3886" ImageSize="2432927" ImageWidth="2560" />
    <Page DoublePage="False" Image="19" ImageHeight="3886" ImageSize="2558963" ImageWidth="2560" />
    <Page DoublePage="False" Image="20" ImageHeight="3886" ImageSize="2619252" ImageWidth="2560" />
    <Page DoublePage="False" Image="21" ImageHeight="3886" ImageSize="1580048" ImageWidth="2560" />
    <Page DoublePage="False" Image="22" ImageHeight="3886" ImageSize="1447649" ImageWidth="2560" />
    <Page DoublePage="False" Image="23" ImageHeight="3886" ImageSize="1821803" ImageWidth="2560" />
    <Page DoublePage="False" Image="24" ImageHeight="3886" ImageSize="2438393" ImageWidth="2560" />
    <Page DoublePage="False" Image="25" ImageHeight="3886" ImageSize="1933282" ImageWidth="2560" />
    <Page DoublePage="False" Image="26" ImageHeight="3886" ImageSize="1712708" ImageWidth="2560" />
  </Pages>
  <Penciller>Emiliano Urdinola</Penciller>
  <Publisher>MERC</Publisher>
  <Series>Deathrage</Series>
  <Volume>2021</Volume>
  <Writer>Murphey</Writer>
  <Year>2022</Year>
  <Summary>(W) Aaron Sparrow &amp; Murphey (A) Emiliano Urdinola (CA) Andrew Mangum Teddy's back and Deathrage is gonna be in trouble! Betrayed, bereft, and bludgeoned beyond belief, can Deathrage possibly overcome the combined might of Teddy, Marla, and their bevy of bloodthirsty bear minions? Or is this the end for our favorite multiple personality MERC with a motormouth?</Summary>
</ComicInfo>