<?xml version='1.0' encoding='utf-8'?>
<ComicInfo xmlns:xsi="http://www.w3.org/2001/XMLSchema-instance" xmlns:xsd="http://www.w3.org/2001/XMLSchema">
  <Series>ALICE</Series>
  <Number>1</Number>
  <Volume>2023</Volume>
  <Genre>Cyperpunk</Genre>
  <Summary>Captain Alice Carroll, USAF scientist is finally bringing her lifelong endeavor to existence. Project Looking Glass is meant to change the world forever but when it doesn’t go as planned Alice’s world is changed in ways she never expected. She finds herself in an alternate reality not too different from her own. Except for the fact that it’s a technocratic empire ruled by the Red Queen and her Hart Foundation.</Summary>
  <Publisher>Bad Beaver Comics</Publisher>
  <Month>12</Month>
  <Year>2023</Year>
  <LanguageISO>en</LanguageISO>
  <Format>Series</Format>
  <AgeRating>Mature 17+</AgeRating>
  <PageCount>31</PageCount>
  <Writer>Matt Ringel</Writer>
  <Penciller>Marika Cresta</Penciller>
  <Inker>Marika Cresta</Inker>
  <Pages>
    <Page DoublePage="False" Image="0" ImageHeight="3884" ImageSize="3291823" ImageWidth="2560" Type="FrontCover" />
    <Page DoublePage="False" Image="1" ImageHeight="3884" ImageSize="2265823" ImageWidth="2560" />
    <Page DoublePage="False" Image="2" ImageHeight="3884" ImageSize="2585208" ImageWidth="2560" />
    <Page DoublePage="False" Image="3" ImageHeight="3884" ImageSize="2432747" ImageWidth="2560" />
    <Page DoublePage="False" Image="4" ImageHeight="3884" ImageSize="2579140" ImageWidth="2560" />
    <Page DoublePage="False" Image="5" ImageHeight="3884" ImageSize="2483692" ImageWidth="2560" />
    <Page DoublePage="False" Image="6" ImageHeight="3884" ImageSize="3220040" ImageWidth="2560" />
    <Page DoublePage="False" Image="7" ImageHeight="3884" ImageSize="2383703" ImageWidth="2560" />
    <Page DoublePage="False" Image="8" ImageHeight="3884" ImageSize="2199501" ImageWidth="2560" />
    <Page DoublePage="True" Image="9" ImageHeight="3884" ImageSize="3717242" ImageWidth="5079" />
    <Page DoublePage="False" Image="10" ImageHeight="3884" ImageSize="1692424" ImageWidth="2560" />
    <Page DoublePage="False" Image="11" ImageHeight="3884" ImageSize="2022736" ImageWidth="2560" />
    <Page DoublePage="False" Image="12" ImageHeight="3884" ImageSize="2107559" ImageWidth="2560" />
    <Page DoublePage="False" Image="13" ImageHeight="3884" ImageSize="2795017" ImageWidth="2560" />
    <Page DoublePage="False" Image="14" ImageHeight="3884" ImageSize="2688488" ImageWidth="2560" />
    <Page DoublePage="False" Image="15" ImageHeight="3884" ImageSize="2317306" ImageWidth="2560" />
    <Page DoublePage="False" Image="16" ImageHeight="3884" ImageSize="2103287" ImageWidth="2560" />
    <Page DoublePage="False" Image="17" ImageHeight="3884" ImageSize="2221674" ImageWidth="2560" />
    <Page DoublePage="False" Image="18" ImageHeight="3884" ImageSize="1896555" ImageWidth="2560" />
    <Page DoublePage="False" Image="19" ImageHeight="3884" ImageSize="1882481" ImageWidth="2560" />
    <Page DoublePage="False" Image="20" ImageHeight="3884" ImageSize="2177467" ImageWidth="2560" />
    <Page DoublePage="False" Image="21" ImageHeight="3884" ImageSize="2266539" ImageWidth="2560" />
    <Page DoublePage="False" Image="22" ImageHeight="3884" ImageSize="1898852" ImageWidth="2560" />
    <Page DoublePage="False" Image="23" ImageHeight="3884" ImageSize="1335878" ImageWidth="2560" />
    <Page DoublePage="False" Image="24" ImageHeight="3884" ImageSize="1788464" ImageWidth="2560" />
    <Page DoublePage="False" Image="25" ImageHeight="3884" ImageSize="1999393" ImageWidth="2560" />
    <Page DoublePage="False" Image="26" ImageHeight="3884" ImageSize="1838443" ImageWidth="2560" />
    <Page DoublePage="False" Image="27" ImageHeight="3884" ImageSize="1961250" ImageWidth="2560" />
    <Page DoublePage="False" Image="28" ImageHeight="3884" ImageSize="2139865" ImageWidth="2560" />
    <Page DoublePage="False" Image="29" ImageHeight="3884" ImageSize="1812813" ImageWidth="2560" />
    <Page DoublePage="False" Image="30" ImageHeight="3884" ImageSize="275573" ImageWidth="2560" />
  </Pages>
</ComicInfo>