<?xml version='1.0' encoding='utf-8'?>
<ComicInfo xmlns:xsi="http://www.w3.org/2001/XMLSchema-instance" xsi:schemaLocation="https://anansi-project.github.io/docs/comicinfo/schemas/v2.1">
  <Characters>Led Dent,Debbie Decay,Davey Trauma,Kazumi,Takara</Characters>
  <Colorist>Dave McCaig,Matt Hollingsworth</Colorist>
  <Day>20</Day>
  <Editor>Sebastian Girner</Editor>
  <GTIN>urn:comicvine:4000-511557</GTIN>
  <Inker>Sean Gordon Murphy</Inker>
  <Letterer>Rus Wooton</Letterer>
  <Locations>Los Angeles,California,Japan,Tokyo</Locations>
  <Month>1</Month>
  <Notes>Tagged with comicbox 1.1.1 on 2024-03-13T17:33:49 [Issue ID 4000-511557] urn:comicvine:4000-511557
Tagged with ComicTagger 1.6.0a13.dev122 using info from Grand Comics Database on 2024-06-16 05:33:51. [Issue ID 1525243]</Notes>
  <Number>5</Number>
  <Pages>
    <Page Image="0" Type="FrontCover" />
    <Page Image="1" />
    <Page Image="2" />
    <Page Image="3" />
    <Page Image="4" />
    <Page Image="5" />
    <Page Image="6" />
    <Page Image="7" />
    <Page Image="8" />
    <Page Image="9" />
    <Page Image="10" />
    <Page Image="11" />
    <Page Image="12" />
    <Page Image="13" />
    <Page Image="14" />
    <Page Image="15" />
    <Page Image="16" />
    <Page Image="17" />
    <Page Image="18" />
    <Page Image="19" />
    <Page Image="20" />
    <Page Image="21" />
    <Page Image="22" />
    <Page Image="23" />
    <Page Image="24" />
    <Page Image="25" />
    <Page Image="26" />
    <Page Image="27" />
    <Page Image="28" />
    <Page Image="29" />
    <Page Image="30" />
  </Pages>
  <Penciller>Sean Gordon Murphy</Penciller>
  <Publisher>Image</Publisher>
  <Series>Tokyo Ghost</Series>
  <Summary>As Eden burns around her, Debbie fights to save the man she loves from the monster he’s become.

*List of covers and their creators:*
| Cover | Name    | Creator(s)                              | Sidebar Location |
|-------|---------|-----------------------------------------|------------------|
| A     | Cover A | Sean Gordon Murphy &amp; Matt Hollingsworth | 1                |
| B     | Cover B | Sean Gordon Murphy &amp; Dave McCaig        | 2                |</Summary>
  <Tags>Led Dent,Los Angeles,Tokyo,Japan,Takara,California,Debbie Decay,Kazumi,Davey Trauma</Tags>
  <Title>I'll Be Your Poison</Title>
  <Volume>2015</Volume>
  <Web>https://comicvine.gamespot.com/tokyo-ghost-5-ill-be-your-poison/4000-511557/</Web>
  <Writer>Rick Remender</Writer>
  <Year>2016</Year>
  <Count>10</Count>
  <CoverArtist>Dave McCaig,Matt Hollingsworth,Sean Gordon Murphy</CoverArtist>
  <Genre>Martial arts,Science fiction,Drama</Genre>
  <LanguageISO>en</LanguageISO>
  <AgeRating>Rated M / Mature</AgeRating>
</ComicInfo>