<ComicInfo xmlns:xsi="http://www.w3.org/2001/XMLSchema-instance" xsi:schemaLocation="https://anansi-project.github.io/docs/comicinfo/schemas/v2.1">
  <Characters>Henry J. Waternoose III,Sulley,Mike Wazowski,Randall Boggs,Fungus,Abominable Snowman,Boo,Bile,George Sanderson</Characters>
  <Editor>Dave Land</Editor>
  <GTIN>urn:comicvine:4000-174709</GTIN>
  <Inker>Davide Zannetti,Sonia Matrone,Sonia Matrone</Inker>
  <Letterer>Jason Hvam,Jason Hvam</Letterer>
  <Locations>Himalayas,Monstropolis</Locations>
  <Month>10</Month>
  <Notes>Tagged with comicbox 1.1.1 on 2024-03-13T23:45:14 [Issue ID 4000-174709] urn:comicvine:4000-174709
Tagged with ComicTagger 1.6.0a13.dev122 using info from Grand Comics Database on 2024-06-18 08:25:46. [Issue ID 713441]</Notes>
  <Number>1</Number>
  <PageCount>48</PageCount>
  <Pages>
    <Page Image="0" ImageHeight="2560" ImageSize="2351936" ImageWidth="1920" Type="FrontCover" />
    <Page Image="1" ImageHeight="2560" ImageSize="2519789" ImageWidth="1920" />
    <Page Image="2" ImageHeight="2560" ImageSize="2454083" ImageWidth="1920" />
    <Page Image="3" ImageHeight="2560" ImageSize="2295168" ImageWidth="1920" />
    <Page Image="4" ImageHeight="2560" ImageSize="2527017" ImageWidth="1920" />
    <Page Image="5" ImageHeight="2560" ImageSize="2386773" ImageWidth="1920" />
    <Page Image="6" ImageHeight="2560" ImageSize="2493506" ImageWidth="1920" />
    <Page Image="7" ImageHeight="2560" ImageSize="2538202" ImageWidth="1920" />
    <Page Image="8" ImageHeight="2560" ImageSize="2534051" ImageWidth="1920" />
    <Page Image="9" ImageHeight="2560" ImageSize="2589693" ImageWidth="1920" />
    <Page Image="10" ImageHeight="2560" ImageSize="2432954" ImageWidth="1920" />
    <Page Image="11" ImageHeight="2560" ImageSize="2505556" ImageWidth="1920" />
    <Page Image="12" ImageHeight="2560" ImageSize="2637343" ImageWidth="1920" />
    <Page Image="13" ImageHeight="2560" ImageSize="2636762" ImageWidth="1920" />
    <Page Image="14" ImageHeight="2560" ImageSize="2464400" ImageWidth="1920" />
    <Page Image="15" ImageHeight="2560" ImageSize="2461988" ImageWidth="1920" />
    <Page Image="16" ImageHeight="2560" ImageSize="2480781" ImageWidth="1920" />
    <Page Image="17" ImageHeight="2560" ImageSize="2573946" ImageWidth="1920" />
    <Page Image="18" ImageHeight="2560" ImageSize="2498355" ImageWidth="1920" />
    <Page Image="19" ImageHeight="2560" ImageSize="2573044" ImageWidth="1920" />
    <Page Image="20" ImageHeight="2560" ImageSize="2724638" ImageWidth="1920" />
    <Page Image="21" ImageHeight="2560" ImageSize="2482990" ImageWidth="1920" />
    <Page Image="22" ImageHeight="2560" ImageSize="2439587" ImageWidth="1920" />
    <Page Image="23" ImageHeight="2560" ImageSize="2464202" ImageWidth="1920" />
    <Page Image="24" ImageHeight="2560" ImageSize="2615285" ImageWidth="1920" />
    <Page Image="25" ImageHeight="2560" ImageSize="2761551" ImageWidth="1920" />
    <Page Image="26" ImageHeight="2560" ImageSize="2635519" ImageWidth="1920" />
    <Page Image="27" ImageHeight="2560" ImageSize="2695986" ImageWidth="1920" />
    <Page Image="28" ImageHeight="2560" ImageSize="2695133" ImageWidth="1920" />
    <Page Image="29" ImageHeight="2560" ImageSize="2589533" ImageWidth="1920" />
    <Page Image="30" ImageHeight="2560" ImageSize="2777314" ImageWidth="1920" />
    <Page Image="31" ImageHeight="2560" ImageSize="2599104" ImageWidth="1920" />
    <Page Image="32" ImageHeight="2560" ImageSize="2471243" ImageWidth="1920" />
    <Page Image="33" ImageHeight="2560" ImageSize="2621033" ImageWidth="1920" />
    <Page Image="34" ImageHeight="2560" ImageSize="2897943" ImageWidth="1920" />
    <Page Image="35" ImageHeight="2560" ImageSize="2762238" ImageWidth="1920" />
    <Page Image="36" ImageHeight="2560" ImageSize="2706473" ImageWidth="1920" />
    <Page Image="37" ImageHeight="2560" ImageSize="2436981" ImageWidth="1920" />
    <Page Image="38" ImageHeight="2560" ImageSize="2661607" ImageWidth="1920" />
    <Page Image="39" ImageHeight="2560" ImageSize="2836695" ImageWidth="1920" />
    <Page Image="40" ImageHeight="2560" ImageSize="2666023" ImageWidth="1920" />
    <Page Image="41" ImageHeight="2560" ImageSize="2502433" ImageWidth="1920" />
    <Page Image="42" ImageHeight="2560" ImageSize="2784346" ImageWidth="1920" />
    <Page Image="43" ImageHeight="2560" ImageSize="2476934" ImageWidth="1920" />
    <Page Image="44" ImageHeight="2560" ImageSize="2507128" ImageWidth="1920" />
    <Page Image="45" ImageHeight="2560" ImageSize="2658641" ImageWidth="1920" />
    <Page Image="46" ImageHeight="2560" ImageSize="2555281" ImageWidth="1920" />
    <Page Image="47" ImageSize="600388" />
  </Pages>
  <Penciller>Anna Merli,Claudio Sciarrone,Elisabetta Melaranci,Elisabetta Melaranci,Anna Merli,Claudio Sciarrone</Penciller>
  <Publisher>Dark Horse</Publisher>
  <ScanInformation>(Digital-GN-) (Son of Ultron-Empire)</ScanInformation>
  <Series>Disney's Monsters, Inc.</Series>
  <Summary>Join a host of spooky yet hardworking monsters as they pop out of closets and try to deliver scares to the children of the world. There's only one catch though -- the Monsters are afraid of the KIDS! When by accident a child ends up in Monsters, Inc. headquarters, mayhem abounds! This graphic adaptation of the Disney/Pixar film Monsters, Inc. is sure to please comics fans and moviegoers as well!

https://comicvine.gamespot.com/monsters-inc-1/4000-174709/</Summary>
  <Teams>Inc.,Monsters</Teams>
  <Volume>2001</Volume>
  <Web>https://comicvine.gamespot.com/monsters-inc-1/4000-174709/</Web>
  <Writer>Charles Bazaldua</Writer>
  <Year>2001</Year>
  <Count>1</Count>
  <Title>Monsters, Inc.</Title>
  <LanguageISO>en</LanguageISO>
  <Format>One-Shot</Format>
  <Colorist>Mara Damiani,Maria Elena Naggi,Mara Damiani,Maria Elena Naggi</Colorist>
<Genre>Comedy,Licensed</Genre></ComicInfo>