<?xml version='1.0' encoding='utf-8'?>
<ComicInfo xmlns:xsi="http://www.w3.org/2001/XMLSchema-instance" xsi:schemaLocation="https://anansi-project.github.io/docs/comicinfo/schemas/v2.1">
  <Characters>John Constantine,Epiphany Greaves: Terry Greaves</Characters>
  <Colorist>Brian Buccellato,Brian Buccellato</Colorist>
  <Editor>Gregory Lockard,Shelly Bond</Editor>
  <GTIN>urn:comicvine:4000-286882</GTIN>
  <Inker>Simon Bisley,Simon Bisley</Inker>
  <Letterer>Sal Cipriano,Sal Cipriano</Letterer>
  <Month>10</Month>
  <Notes>Tagged with comicbox 1.1.1 on 2024-03-13T21:02:12 [Issue ID 4000-286882] urn:comicvine:4000-286882
Tagged with ComicTagger 1.6.0a13.dev122 using info from Grand Comics Database on 2024-06-16 22:17:44. [Issue ID 869475]</Notes>
  <Number>282</Number>
  <PageCount>21</PageCount>
  <Pages>
    <Page Image="0" ImageSize="1256975" Type="FrontCover" />
    <Page Image="1" ImageSize="930845" />
    <Page Image="2" ImageSize="1178966" />
    <Page Image="3" ImageSize="956229" />
    <Page Image="4" ImageSize="1353609" />
    <Page Image="5" ImageSize="1332136" />
    <Page Image="6" ImageSize="1164019" />
    <Page Image="7" ImageSize="1171854" />
    <Page Image="8" ImageSize="1127407" />
    <Page Image="9" ImageSize="1222458" />
    <Page Image="10" ImageSize="1196681" />
    <Page Image="11" ImageSize="1022745" />
    <Page Image="12" ImageSize="1537823" />
    <Page Image="13" ImageSize="1227200" />
    <Page Image="14" ImageSize="1169626" />
    <Page Image="15" ImageSize="1092472" />
    <Page Image="16" ImageSize="1045483" />
    <Page Image="17" ImageSize="1117675" />
    <Page Image="18" ImageSize="1080138" />
    <Page Image="19" ImageSize="1173172" />
    <Page Image="20" ImageSize="1158548" />
  </Pages>
  <Penciller>Simon Bisley,Simon Bisley</Penciller>
  <Publisher>DC Comics</Publisher>
  <Series>Hellblazer</Series>
  <Summary>Don't miss this startling stand-alone tale! In a British prison, a shape-shifting product of the Babylonian backstreets called Julian is about to have some fun at the prisoners' expense. Now, the prison has become a kind of living Hell – even more than before – which should make John Constantine feel right at home when he poses as an inmate and tries to dish out his own rough justice to demonic prisoner number 666.

Tagged with the ninjas.walk.alone fork of ComicTagger 1.3.5 using info from Comic Vine on 2023-07-27 10:19:31.  [CVDB286882]

https://comicvine.gamespot.com/hellblazer-282-inside/4000-286882/</Summary>
  <Title>Inside</Title>
  <Volume>1988</Volume>
  <Web>https://comicvine.gamespot.com/hellblazer-282-inside/4000-286882/</Web>
  <Writer>Peter Milligan,Peter Milligan</Writer>
  <Year>2011</Year>
  <Count>300</Count>
  <Genre>Horror-suspense</Genre>
  <LanguageISO>en</LanguageISO>
  <AgeRating>Suggested for Mature Readers</AgeRating>
</ComicInfo>