<?xml version="1.0"?>
<ComicInfo xmlns:xsi="http://www.w3.org/2001/XMLSchema-instance" xmlns:xsd="http://www.w3.org/2001/XMLSchema">
  <Title>The Justly Compensated League of Super-heroes!</Title>
  <Series>The Tick: Karma Tornado</Series>
  <Number>5</Number>
  <Volume>1993</Volume>
  <Summary>The Tick encounters THE JUSTLY COMPENSATED LEAGUE OF SUPER-HERO a group of heroes who ask for payment for their good deeds! The Tick decides to join this group which leeds to disaster... of course.</Summary>
  <Notes>Tagged with the ninjas.walk.alone fork of ComicTagger 1.3.5 using info from Comic Vine on 2024-05-15 11:13:47.  [CVDB216854]</Notes>
  <Year>1994</Year>
  <Month>08</Month>
  <Day>01</Day>
  <Publisher>New England Comics</Publisher>
  <Web>https://comicvine.gamespot.com/the-tick-karma-tornado-5-the-justly-compensated-le/4000-216854/</Web>
  <PageCount>25</PageCount>
  <Characters>Arthur, The Tick</Characters>
  <Pages>
    <Page Image="0" Type="FrontCover" ImageSize="592920" />
    <Page Image="1" ImageSize="548584" />
    <Page Image="2" ImageSize="855022" />
    <Page Image="3" ImageSize="578122" />
    <Page Image="4" ImageSize="945712" />
    <Page Image="5" ImageSize="871422" />
    <Page Image="6" ImageSize="661092" />
    <Page Image="7" ImageSize="670608" />
    <Page Image="8" ImageSize="601232" />
    <Page Image="9" ImageSize="725260" />
    <Page Image="10" ImageSize="809074" />
    <Page Image="11" ImageSize="610240" />
    <Page Image="12" ImageSize="651510" />
    <Page Image="13" ImageSize="698226" />
    <Page Image="14" ImageSize="616954" />
    <Page Image="15" ImageSize="732718" />
    <Page Image="16" ImageSize="650206" />
    <Page Image="17" ImageSize="541412" />
    <Page Image="18" ImageSize="554388" />
    <Page Image="19" ImageSize="573292" />
    <Page Image="20" ImageSize="758162" />
    <Page Image="21" ImageSize="693056" />
    <Page Image="22" ImageSize="792928" />
    <Page Image="23" ImageSize="884238" />
    <Page Image="24" ImageSize="678968" />
  </Pages>
</ComicInfo>
