<?xml version='1.0' encoding='utf-8'?>
<ComicInfo xmlns:xsi="http://www.w3.org/2001/XMLSchema-instance" xsi:schemaLocation="https://anansi-project.github.io/docs/comicinfo/schemas/v2.1">
  <Characters>Betty,Dee,Violet,Hannah</Characters>
  <Editor>Jim Valentino,Laura Tavishati</Editor>
  <GTIN>urn:comicvine:4000-442118</GTIN>
  <Inker>John Upchurch,Roc Upchurch,Roc Upchurch</Inker>
  <Letterer>Ed Brisson,Ed Brisson</Letterer>
  <Month>1</Month>
  <Notes>Tagged with comicbox 1.1.1 on 2024-03-13T17:45:50 [Issue ID 4000-442118] urn:comicvine:4000-442118
Tagged with ComicTagger 1.6.0a13.dev122 using info from Grand Comics Database on 2024-06-16 06:27:58. [Issue ID 1173582]</Notes>
  <Number>4</Number>
  <Pages>
    <Page Image="0" Type="FrontCover" />
    <Page Image="1" />
    <Page Image="2" />
    <Page Image="3" />
    <Page Image="4" />
    <Page Image="5" />
    <Page Image="6" />
    <Page Image="7" />
    <Page Image="8" />
    <Page Image="9" />
    <Page Image="10" />
    <Page Image="11" />
    <Page Image="12" />
    <Page Image="13" />
    <Page Image="14" />
    <Page Image="15" />
    <Page Image="16" />
    <Page Image="17" />
    <Page Image="18" />
    <Page Image="19" />
    <Page Image="20" />
    <Page Image="21" />
    <Page Image="22" />
    <Page Image="23" />
    <Page Image="24" />
    <Page Image="25" />
    <Page Image="26" />
    <Page Image="27" />
    <Page Image="28" />
    <Page Image="29" />
    <Page Image="30" />
    <Page Image="31" />
    <Page Image="32" />
  </Pages>
  <Penciller>John Upchurch,Roc Upchurch,Roc Upchurch</Penciller>
  <Publisher>Image</Publisher>
  <Series>Rat Queens</Series>
  <Summary>“GOLD, GUTS, AND GROG,” Part Four

Holy vengeance can be a real headache, but it's so much worse when it's coming from a fifteen foot tall lady troll who's just lost her dad. In this blood-splattered issue, the Rat Queens find out that every action has some sort of hilariously brutal consequence!</Summary>
  <Tags>Betty,Gary,Sawyer Silver,Rat Queens,Violet,Braga,Lady Bernadette,Dee,Four Daves,Orc Dave,Hannah</Tags>
  <Teams>Rat Queens,Four Daves</Teams>
  <Title>Gold, Guts and Grog, Part 4</Title>
  <Volume>2013</Volume>
  <Web>https://comicvine.gamespot.com/rat-queens-4-gold-guts-and-grog-part-4/4000-442118/</Web>
  <Writer>Kurtis J. Wiebe,Kurtis J. Wiebe</Writer>
  <Year>2014</Year>
  <Count>16</Count>
  <CoverArtist>John Upchurch</CoverArtist>
  <Genre>Fantasy</Genre>
  <LanguageISO>en</LanguageISO>
  <AgeRating>Rated M / Mature</AgeRating>
  <Colorist>Roc Upchurch,Roc Upchurch</Colorist>
</ComicInfo>