<?xml version='1.0' encoding='utf-8'?>
<ComicInfo>
  <Series>Elvira, Mistress of the Dark</Series>
  <Number>37</Number>
  <Count>166</Count>
  <Volume>1993</Volume>
  <Summary>Elvira's most critical adventure yet, as she heads to the secret settlement of Gorilla Town, just in time to become the target of its most deadly danger, Pete Primate! "Crisis in Gorilla Town. "

 The back-up concludes the story of Elvira's station manager's nice twin, and the evil plan that created her!</Summary>
  <Notes>Tagged with the ninjas.walk.alone fork of ComicTagger 1.3.5 using info from Comic Vine on 2024-06-02 23:11:13.  [CVDB145127]
Tagged with ComicTagger 1.6.0a13.dev122 using info from Grand Comics Database on 2024-06-17 13:20:59. [Issue ID 243455]</Notes>
  <Year>1996</Year>
  <Month>5</Month>
  <Publisher>Claypool Comics</Publisher>
  <Web>https://comicvine.gamespot.com/elvira-mistress-of-the-dark-37/4000-145127/</Web>
  <PageCount>28</PageCount>
  <LanguageISO>en</LanguageISO>
  <Characters>Elvira</Characters>
  <Pages>
    <Page Image="0" ImageSize="691264" Type="FrontCover" />
    <Page Image="1" ImageSize="554795" />
    <Page Image="2" ImageSize="652128" />
    <Page Image="3" ImageSize="641112" />
    <Page Image="4" ImageSize="607884" />
    <Page Image="5" ImageSize="602524" />
    <Page Image="6" ImageSize="640433" />
    <Page Image="7" ImageSize="705830" />
    <Page Image="8" ImageSize="670661" />
    <Page Image="9" ImageSize="589275" />
    <Page Image="10" ImageSize="698379" />
    <Page Image="11" ImageSize="663435" />
    <Page Image="12" ImageSize="676838" />
    <Page Image="13" ImageSize="615917" />
    <Page Image="14" ImageSize="615442" />
    <Page Image="15" ImageSize="633082" />
    <Page Image="16" ImageSize="637092" />
    <Page Image="17" ImageSize="632247" />
    <Page Image="18" ImageSize="696534" />
    <Page Image="19" ImageSize="674827" />
    <Page Image="20" ImageSize="758445" />
    <Page Image="21" ImageSize="691729" />
    <Page Image="22" ImageSize="692305" />
    <Page Image="23" ImageSize="705755" />
    <Page Image="24" ImageSize="696968" />
    <Page Image="25" ImageSize="773509" />
    <Page Image="26" ImageSize="687294" />
    <Page Image="27" ImageSize="722016" />
  </Pages>
</ComicInfo>