<ComicInfo xmlns:xsi="http://www.w3.org/2001/XMLSchema-instance" xsi:schemaLocation="https://anansi-project.github.io/docs/comicinfo/schemas/v2.1">
  <Characters>Vana,Skyman,Captain Future,Liberator,Kitten,Fighting Yank,Green Lama,Super-American,Rocketgirl,Captain Courageous,The Flame,Raven,Black Owl,Flame Girl,Dyna Might,Red Sonja,Vampirella,The Sword,The Hood,Woman In Red</Characters>
  <Colorist>Ellie Wright</Colorist>
  <Count>5</Count>
  <Day>8</Day>
  <Editor>Joseph Rybandt,Luke Lieberman,Nate Cosby</Editor>
  <GTIN>urn:comicvine:4000-971518</GTIN>
  <Letterer>Jeff Eckleberry</Letterer>
  <Month>2</Month>
  <Notes>Tagged with comicbox 1.1.1 on 2024-03-14T03:09:53 [Issue ID 4000-971518] urn:comicvine:4000-971518
Tagged with ComicTagger 1.6.0a13.dev122 using info from Grand Comics Database on 2024-06-18 19:20:01. [Issue ID 2493040]</Notes>
  <Number>4</Number>
  <PageCount>29</PageCount>
  <Pages>
    <Page Image="0" ImageSize="679615" Type="FrontCover" />
    <Page Image="1" ImageSize="4012782" />
    <Page Image="2" ImageSize="1875563" />
    <Page Image="3" ImageSize="1718796" />
    <Page Image="4" ImageSize="1055935" />
    <Page Image="5" ImageSize="992817" />
    <Page Image="6" ImageSize="1299656" />
    <Page Image="7" ImageSize="5615956" />
    <Page Image="8" ImageSize="1239116" />
    <Page Image="9" ImageSize="1057853" />
    <Page Image="10" ImageSize="6530289" />
    <Page Image="11" ImageSize="5993365" />
    <Page Image="12" ImageSize="1462213" />
    <Page Image="13" ImageSize="1227400" />
    <Page Image="14" ImageSize="1270728" />
    <Page Image="15" ImageSize="1037661" />
    <Page Image="16" ImageSize="1424980" />
    <Page Image="17" ImageSize="1160211" />
    <Page Image="18" ImageSize="1206693" />
    <Page Image="19" ImageSize="1527795" />
    <Page Image="20" ImageSize="1254502" />
    <Page Image="21" ImageSize="1671515" />
    <Page Image="22" ImageSize="1530197" />
    <Page Image="23" ImageSize="1121613" />
    <Page Image="24" ImageSize="1143670" />
    <Page Image="25" ImageSize="893144" />
    <Page Image="26" ImageSize="1452028" />
    <Page Image="27" ImageSize="1233907" />
    <Page Image="28" ImageSize="1204289" />
  </Pages>
  <Publisher>Dynamite Entertainment</Publisher>
  <Series>Vampirella versus Red Sonja</Series>
  <Summary>THE GALAXY’S HEROES BELIEVE VAMPIRELLA IS TRYING TO DESTROY THEIR WORLDS!

The grand battle and greater war rages on. How can Vampirella clear her name when every superhero in existence believes she’s trying to destroy their worlds? Will Red Sonja allow her suspicions to lead her to the truth, or will her lust for battle overwhelm all reason?</Summary>
  <Tags>Vana,Skyman,Captain Future,Liberator,Kitten,Fighting Yank,Green Lama,Super-American,Rocketgirl,Captain Courageous,The Flame,Raven,Black Owl,Flame Girl,Dyna Might,Red Sonja,Vampirella,The Sword,The Hood,Woman In Red</Tags>
  <Volume>2022</Volume>
  <Web>https://comicvine.gamespot.com/vampirella-versus-red-sonja-4/4000-971518/</Web>
  <Writer>Dan Abnett</Writer>
  <Year>2023</Year>
  <LanguageISO>en</LanguageISO>
  <Format>Limited Series</Format>
  <AgeRating>Rated Teen+</AgeRating>
<Genre>Fantasy</Genre></ComicInfo>